localmapper/__init__.py
localmapper/localmapper.py
localmapper/mapper.py
localmapper/model_utils.py
localmapper/models.py
localmapper/utils.py
localmapper/LocalTemplate/template_extract_extention.py
localmapper/LocalTemplate/template_extract_utils.py
localmapper/LocalTemplate/template_extractor.py
localmapper/data/LocalMapper_202403.pth
localmapper/data/default_config.json
localmapper/data/templates_202403.pkl
localmapper-1.0.dist-info/LICENSE
localmapper-1.0.dist-info/METADATA
localmapper-1.0.dist-info/WHEEL
localmapper-1.0.dist-info/top_level.txt
localmapper-1.0.dist-info/RECORD
