Metadata-Version: 2.1
Name: localmapper
Version: 1.0
Summary: LocalMapper for precise reaction atom-mapping
Home-page: UNKNOWN
Author: Shuan Chen
License: The GNU General Public License v3.0
Platform: UNKNOWN
Requires-Python: >=3.6
License-File: LICENSE
Requires-Dist: numpy (>=1.16.4)
Requires-Dist: matplotlib (>=3.3.4)
Requires-Dist: torch (>=1.0.0)
Requires-Dist: dgl (>=0.5.2)
Requires-Dist: dgllife (>=0.2.6)
Provides-Extra: rdkit
Requires-Dist: rdkit-pypi (>=2021.3.2) ; (python_version < "3.7") and extra == 'rdkit'
Requires-Dist: rdkit (>=2022.3.4) ; (python_version >= "3.7") and extra == 'rdkit'
